[
  {
    "ContainingType": "Kemar.WHL.API.Controller.AuthController",
    "Method": "ChangePassword",
    "RelativePath": "api/Auth/change-password",
    "HttpMethod": "POST",
    "IsController": true,
    "Order": 0,
    "Parameters": [
      {
        "Name": "req",
        "Type": "ChangePasswordRequest",
        "IsRequired": true
      }
    ],
    "ReturnTypes": []
  },
  {
    "ContainingType": "Kemar.WHL.API.Controller.AuthController",
    "Method": "ForgotPassword",
    "RelativePath": "api/Auth/forgot-password",
    "HttpMethod": "POST",
    "IsController": true,
    "Order": 0,
    "Parameters": [
      {
        "Name": "req",
        "Type": "Kemar.WHL.Model.Request.ForgotPasswordRequest",
        "IsRequired": true
      }
    ],
    "ReturnTypes": []
  },
  {
    "ContainingType": "Kemar.WHL.API.Controller.AuthController",
    "Method": "Login",
    "RelativePath": "api/Auth/login",
    "HttpMethod": "POST",
    "IsController": true,
    "Order": 0,
    "Parameters": [
      {
        "Name": "req",
        "Type": "Kemar.WHL.API.Controller.AuthController\u002BLoginRequest",
        "IsRequired": true
      }
    ],
    "ReturnTypes": []
  },
  {
    "ContainingType": "Kemar.WHL.API.Controllers.DistanceController",
    "Method": "GetById",
    "RelativePath": "api/Distance/{id}",
    "HttpMethod": "GET",
    "IsController": true,
    "Order": 0,
    "Parameters": [
      {
        "Name": "id",
        "Type": "System.Int32",
        "IsRequired": true
      }
    ],
    "ReturnTypes": []
  },
  {
    "ContainingType": "Kemar.WHL.API.Controllers.DistanceController",
    "Method": "Delete",
    "RelativePath": "api/Distance/{id}",
    "HttpMethod": "DELETE",
    "IsController": true,
    "Order": 0,
    "Parameters": [
      {
        "Name": "id",
        "Type": "System.Int32",
        "IsRequired": true
      }
    ],
    "ReturnTypes": []
  },
  {
    "ContainingType": "Kemar.WHL.API.Controllers.DistanceController",
    "Method": "AddOrUpdate",
    "RelativePath": "api/Distance/add-or-update",
    "HttpMethod": "POST",
    "IsController": true,
    "Order": 0,
    "Parameters": [
      {
        "Name": "request",
        "Type": "Kemar.WHL.Model.Request.DistanceRequest",
        "IsRequired": true
      }
    ],
    "ReturnTypes": []
  },
  {
    "ContainingType": "Kemar.WHL.API.Controllers.DistanceController",
    "Method": "GetAll",
    "RelativePath": "api/Distance/all",
    "HttpMethod": "GET",
    "IsController": true,
    "Order": 0,
    "Parameters": [],
    "ReturnTypes": []
  },
  {
    "ContainingType": "Kemar.WHL.API.Controllers.DistanceController",
    "Method": "GetByFilter",
    "RelativePath": "api/Distance/filter",
    "HttpMethod": "POST",
    "IsController": true,
    "Order": 0,
    "Parameters": [
      {
        "Name": "filter",
        "Type": "Kemar.WHL.Model.Request.DistanceFilterModel",
        "IsRequired": true
      }
    ],
    "ReturnTypes": []
  },
  {
    "ContainingType": "InventoryController",
    "Method": "GetById",
    "RelativePath": "api/Inventory/{id}",
    "HttpMethod": "GET",
    "IsController": true,
    "Order": 0,
    "Parameters": [
      {
        "Name": "id",
        "Type": "System.Int32",
        "IsRequired": true
      }
    ],
    "ReturnTypes": []
  },
  {
    "ContainingType": "InventoryController",
    "Method": "Delete",
    "RelativePath": "api/Inventory/{id}",
    "HttpMethod": "DELETE",
    "IsController": true,
    "Order": 0,
    "Parameters": [
      {
        "Name": "id",
        "Type": "System.Int32",
        "IsRequired": true
      }
    ],
    "ReturnTypes": []
  },
  {
    "ContainingType": "InventoryController",
    "Method": "AddOrUpdate",
    "RelativePath": "api/Inventory/add-or-update",
    "HttpMethod": "POST",
    "IsController": true,
    "Order": 0,
    "Parameters": [
      {
        "Name": "request",
        "Type": "Kemar.WHL.Model.Request.InventoryRequest",
        "IsRequired": true
      }
    ],
    "ReturnTypes": []
  },
  {
    "ContainingType": "InventoryController",
    "Method": "GetAll",
    "RelativePath": "api/Inventory/all",
    "HttpMethod": "GET",
    "IsController": true,
    "Order": 0,
    "Parameters": [],
    "ReturnTypes": []
  },
  {
    "ContainingType": "InventoryController",
    "Method": "GetByFilter",
    "RelativePath": "api/Inventory/filter",
    "HttpMethod": "POST",
    "IsController": true,
    "Order": 0,
    "Parameters": [
      {
        "Name": "filter",
        "Type": "InventoryFilterModel",
        "IsRequired": true
      }
    ],
    "ReturnTypes": []
  },
  {
    "ContainingType": "PickingController",
    "Method": "GetByShipment",
    "RelativePath": "api/Picking/by-shipment/{shipmentId}",
    "HttpMethod": "GET",
    "IsController": true,
    "Order": 0,
    "Parameters": [
      {
        "Name": "shipmentId",
        "Type": "System.Int32",
        "IsRequired": true
      }
    ],
    "ReturnTypes": []
  },
  {
    "ContainingType": "PickingController",
    "Method": "Pick",
    "RelativePath": "api/Picking/pick",
    "HttpMethod": "POST",
    "IsController": true,
    "Order": 0,
    "Parameters": [
      {
        "Name": "request",
        "Type": "PickingRequest",
        "IsRequired": true
      }
    ],
    "ReturnTypes": []
  },
  {
    "ContainingType": "ProductController",
    "Method": "GetAll",
    "RelativePath": "api/Product",
    "HttpMethod": "GET",
    "IsController": true,
    "Order": 0,
    "Parameters": [],
    "ReturnTypes": []
  },
  {
    "ContainingType": "ProductController",
    "Method": "GetById",
    "RelativePath": "api/Product/{id}",
    "HttpMethod": "GET",
    "IsController": true,
    "Order": 0,
    "Parameters": [
      {
        "Name": "id",
        "Type": "System.Int32",
        "IsRequired": true
      }
    ],
    "ReturnTypes": []
  },
  {
    "ContainingType": "ProductController",
    "Method": "Delete",
    "RelativePath": "api/Product/{id}",
    "HttpMethod": "DELETE",
    "IsController": true,
    "Order": 0,
    "Parameters": [
      {
        "Name": "id",
        "Type": "System.Int32",
        "IsRequired": true
      }
    ],
    "ReturnTypes": []
  },
  {
    "ContainingType": "ProductController",
    "Method": "AddOrUpdate",
    "RelativePath": "api/Product/add-or-update",
    "HttpMethod": "POST",
    "IsController": true,
    "Order": 0,
    "Parameters": [
      {
        "Name": "request",
        "Type": "Kemar.WHL.Model.Request.ProductRequest",
        "IsRequired": true
      }
    ],
    "ReturnTypes": []
  },
  {
    "ContainingType": "ProductController",
    "Method": "Filter",
    "RelativePath": "api/Product/filter",
    "HttpMethod": "POST",
    "IsController": true,
    "Order": 0,
    "Parameters": [
      {
        "Name": "filter",
        "Type": "Kemar.WHL.Model.Request.ProductFilterRequest",
        "IsRequired": true
      }
    ],
    "ReturnTypes": []
  },
  {
    "ContainingType": "ShipmentController",
    "Method": "GetById",
    "RelativePath": "api/Shipment/{id}",
    "HttpMethod": "GET",
    "IsController": true,
    "Order": 0,
    "Parameters": [
      {
        "Name": "id",
        "Type": "System.Int32",
        "IsRequired": true
      }
    ],
    "ReturnTypes": []
  },
  {
    "ContainingType": "ShipmentController",
    "Method": "Delete",
    "RelativePath": "api/Shipment/{id}",
    "HttpMethod": "DELETE",
    "IsController": true,
    "Order": 0,
    "Parameters": [
      {
        "Name": "id",
        "Type": "System.Int32",
        "IsRequired": true
      }
    ],
    "ReturnTypes": []
  },
  {
    "ContainingType": "ShipmentController",
    "Method": "AddOrUpdate",
    "RelativePath": "api/Shipment/add-or-update",
    "HttpMethod": "POST",
    "IsController": true,
    "Order": 0,
    "Parameters": [
      {
        "Name": "request",
        "Type": "Kemar.WHL.Model.Request.ShipmentRequest",
        "IsRequired": true
      }
    ],
    "ReturnTypes": []
  },
  {
    "ContainingType": "ShipmentController",
    "Method": "GetAll",
    "RelativePath": "api/Shipment/all",
    "HttpMethod": "GET",
    "IsController": true,
    "Order": 0,
    "Parameters": [],
    "ReturnTypes": []
  },
  {
    "ContainingType": "ShipmentController",
    "Method": "GetByFilter",
    "RelativePath": "api/Shipment/filter",
    "HttpMethod": "POST",
    "IsController": true,
    "Order": 0,
    "Parameters": [
      {
        "Name": "filter",
        "Type": "kemar.WHL.Model.Filter.ShipmentFilterModel",
        "IsRequired": true
      }
    ],
    "ReturnTypes": []
  },
  {
    "ContainingType": "UserController",
    "Method": "GetById",
    "RelativePath": "api/User/{id}",
    "HttpMethod": "GET",
    "IsController": true,
    "Order": 0,
    "Parameters": [
      {
        "Name": "id",
        "Type": "System.Int32",
        "IsRequired": true
      }
    ],
    "ReturnTypes": []
  },
  {
    "ContainingType": "UserController",
    "Method": "Delete",
    "RelativePath": "api/User/{id}",
    "HttpMethod": "DELETE",
    "IsController": true,
    "Order": 0,
    "Parameters": [
      {
        "Name": "id",
        "Type": "System.Int32",
        "IsRequired": true
      }
    ],
    "ReturnTypes": []
  },
  {
    "ContainingType": "UserController",
    "Method": "AddOrUpdate",
    "RelativePath": "api/User/add-or-update",
    "HttpMethod": "POST",
    "IsController": true,
    "Order": 0,
    "Parameters": [
      {
        "Name": "request",
        "Type": "Kemar.WHL.Repository.Models.User.UserRequest",
        "IsRequired": true
      }
    ],
    "ReturnTypes": []
  },
  {
    "ContainingType": "UserController",
    "Method": "GetAll",
    "RelativePath": "api/User/all",
    "HttpMethod": "GET",
    "IsController": true,
    "Order": 0,
    "Parameters": [],
    "ReturnTypes": []
  },
  {
    "ContainingType": "UserController",
    "Method": "Filter",
    "RelativePath": "api/User/filter",
    "HttpMethod": "POST",
    "IsController": true,
    "Order": 0,
    "Parameters": [
      {
        "Name": "filter",
        "Type": "kemar.WHL.Model.Filter.UserFilterModel",
        "IsRequired": true
      }
    ],
    "ReturnTypes": []
  },
  {
    "ContainingType": "VehicleController",
    "Method": "GetById",
    "RelativePath": "api/Vehicle/{id}",
    "HttpMethod": "GET",
    "IsController": true,
    "Order": 0,
    "Parameters": [
      {
        "Name": "id",
        "Type": "System.Int32",
        "IsRequired": true
      }
    ],
    "ReturnTypes": []
  },
  {
    "ContainingType": "VehicleController",
    "Method": "Delete",
    "RelativePath": "api/Vehicle/{id}",
    "HttpMethod": "DELETE",
    "IsController": true,
    "Order": 0,
    "Parameters": [
      {
        "Name": "id",
        "Type": "System.Int32",
        "IsRequired": true
      }
    ],
    "ReturnTypes": []
  },
  {
    "ContainingType": "VehicleController",
    "Method": "AddOrUpdate",
    "RelativePath": "api/Vehicle/add-or-update",
    "HttpMethod": "POST",
    "IsController": true,
    "Order": 0,
    "Parameters": [
      {
        "Name": "request",
        "Type": "Kemar.WHL.Model.Request.VehicleRequest",
        "IsRequired": true
      }
    ],
    "ReturnTypes": []
  },
  {
    "ContainingType": "VehicleController",
    "Method": "GetAll",
    "RelativePath": "api/Vehicle/all",
    "HttpMethod": "GET",
    "IsController": true,
    "Order": 0,
    "Parameters": [],
    "ReturnTypes": []
  },
  {
    "ContainingType": "VehicleController",
    "Method": "GetByFilter",
    "RelativePath": "api/Vehicle/filter",
    "HttpMethod": "POST",
    "IsController": true,
    "Order": 0,
    "Parameters": [
      {
        "Name": "filter",
        "Type": "Kemar.WHL.Model.Request.VehicleFilterRequest",
        "IsRequired": true
      }
    ],
    "ReturnTypes": []
  },
  {
    "ContainingType": "WarehouseController",
    "Method": "GetById",
    "RelativePath": "api/Warehouse/{id}",
    "HttpMethod": "GET",
    "IsController": true,
    "Order": 0,
    "Parameters": [
      {
        "Name": "id",
        "Type": "System.Int32",
        "IsRequired": true
      }
    ],
    "ReturnTypes": []
  },
  {
    "ContainingType": "WarehouseController",
    "Method": "Delete",
    "RelativePath": "api/Warehouse/{id}",
    "HttpMethod": "DELETE",
    "IsController": true,
    "Order": 0,
    "Parameters": [
      {
        "Name": "id",
        "Type": "System.Int32",
        "IsRequired": true
      }
    ],
    "ReturnTypes": []
  },
  {
    "ContainingType": "WarehouseController",
    "Method": "AddOrUpdate",
    "RelativePath": "api/Warehouse/add-or-update",
    "HttpMethod": "POST",
    "IsController": true,
    "Order": 0,
    "Parameters": [
      {
        "Name": "request",
        "Type": "Kemar.WHL.Model.Request.WarehouseRequest",
        "IsRequired": true
      }
    ],
    "ReturnTypes": []
  },
  {
    "ContainingType": "WarehouseController",
    "Method": "GetAll",
    "RelativePath": "api/Warehouse/all",
    "HttpMethod": "GET",
    "IsController": true,
    "Order": 0,
    "Parameters": [],
    "ReturnTypes": []
  },
  {
    "ContainingType": "WarehouseController",
    "Method": "GetByFilter",
    "RelativePath": "api/Warehouse/filter",
    "HttpMethod": "POST",
    "IsController": true,
    "Order": 0,
    "Parameters": [
      {
        "Name": "filter",
        "Type": "WarehouseFilterModel",
        "IsRequired": true
      }
    ],
    "ReturnTypes": []
  }
]